MotifDiff/MotifDiff.py
MotifDiff/__init__.py
MotifDiff/util.py
MotifDiff_pkg-1.5.dist-info/METADATA
MotifDiff_pkg-1.5.dist-info/WHEEL
MotifDiff_pkg-1.5.dist-info/entry_points.txt
MotifDiff_pkg-1.5.dist-info/top_level.txt
MotifDiff_pkg-1.5.dist-info/RECORD
