Metadata-Version: 2.1
Name: MotifDiff-pkg
Version: 1.5
Requires-Dist: typer
Requires-Dist: torch
Requires-Dist: numpy
Requires-Dist: pandas
Requires-Dist: pysam
Requires-Dist: scipy
Requires-Dist: regex
